odoo/addons/web_editor_background_color/README.rst
odoo/addons/web_editor_background_color/__init__.py
odoo/addons/web_editor_background_color/__manifest__.py
odoo/addons/web_editor_background_color/i18n/ca.po
odoo/addons/web_editor_background_color/i18n/es.po
odoo/addons/web_editor_background_color/i18n/fr.po
odoo/addons/web_editor_background_color/i18n/pt_BR.po
odoo/addons/web_editor_background_color/i18n/sl.po
odoo/addons/web_editor_background_color/i18n/web_editor_background_color.pot
odoo/addons/web_editor_background_color/i18n/zh_CN.po
odoo/addons/web_editor_background_color/readme/CONTRIBUTORS.rst
odoo/addons/web_editor_background_color/readme/CREDITS.rst
odoo/addons/web_editor_background_color/readme/DESCRIPTION.rst
odoo/addons/web_editor_background_color/readme/ROADMAP.rst
odoo/addons/web_editor_background_color/readme/USAGE.rst
odoo/addons/web_editor_background_color/static/description/icon.png
odoo/addons/web_editor_background_color/static/description/index.html
odoo/addons/web_editor_background_color/static/src/css/background_color.scss
odoo/addons/web_editor_background_color/static/src/js/background_color.js
odoo/addons/web_editor_background_color/templates/assets.xml
odoo/addons/web_editor_background_color/templates/editor.xml
odoo12_addon_web_editor_background_color-12.0.1.0.0.99.dev8.dist-info/METADATA
odoo12_addon_web_editor_background_color-12.0.1.0.0.99.dev8.dist-info/WHEEL
odoo12_addon_web_editor_background_color-12.0.1.0.0.99.dev8.dist-info/top_level.txt
odoo12_addon_web_editor_background_color-12.0.1.0.0.99.dev8.dist-info/RECORD
